ticguide/__init__.py
ticguide/cli.py
ticguide/pipeline.py
ticguide/version.py
ticguide-0.5.2.dist-info/LICENSE
ticguide-0.5.2.dist-info/METADATA
ticguide-0.5.2.dist-info/WHEEL
ticguide-0.5.2.dist-info/entry_points.txt
ticguide-0.5.2.dist-info/top_level.txt
ticguide-0.5.2.dist-info/RECORD
