Metadata-Version: 2.1
Name: ticguide
Version: 0.5.2
Summary: quick + painless TESS observing information
Home-page: https://github.com/ashleychontos/ticguide
Author: Ashley Chontos
Author-email: ashleychontos@astro.princeton.edu
License: MIT
Project-URL: Source, https://github.com/ashleychontos/ticguide
Project-URL: Bug Tracker, https://github.com/ashleychontos/ticguide/issues
Classifier: Programming Language :: Python :: 3
Classifier: License :: OSI Approved :: MIT License
Classifier: Operating System :: OS Independent
Requires-Python: >=3.6
License-File: LICENSE
Requires-Dist: numpy
Requires-Dist: pandas >=1.0.5
Requires-Dist: tqdm
Requires-Dist: bs4
